{
    "homepage": "https://github.com/maokwen/LockMicrosoftPinyin",
    "description": "Lock Microsoft Pinyin IME on Chinese status",
    "version": "2022-06-01",
    "license": "Unlicense",
    "url": "https://github.com/maokwen/LockMicrosoftPinyin/releases/download/2022-06-01/LockMicrosoftPinyin.zip",
    "hash": "eed3740f7d9a6fa43be757a33ce179236eb4d50bf53f7510c0827c1bc00ea54d",
    "shortcuts": [
        [
            "LockMicrosoftPinyin.exe",
            "LockMicrosoftPinyin"
        ]
    ],
    "checkver": {
        "url": "https://github.com/maokwen/LockMicrosoftPinyin/releases",
        "regex": "/releases/tag/([\\d-]+)"
    },
    "autoupdate": {
        "url": "https://github.com/maokwen/LockMicrosoftPinyin/releases/download/$version/LockMicrosoftPinyin.zip"
    }
}
