{
    "homepage": "https://outerwildsmods.com/",
    "description": "Mod manager for Outer Wilds",
    "version": "1.10.1",
    "license": "MIT",
    "url": "https://github.com/Raicuparta/ow-mod-manager/releases/download/v1.10.1/OuterWildsModManager-Portable.zip",
    "hash": "e49fb004502c5651bb33553fb6d7c2440f6b4c11011cc25b55480a85a96dbd1b",
    "shortcuts": [
        [
            "OuterWildsModManager.exe",
            "Outer Wilds Mod Manager"
        ]
    ],
    "checkver": {
        "github": "https://github.com/Raicuparta/ow-mod-manager"
    },
    "autoupdate": {
        "url": "https://github.com/Raicuparta/ow-mod-manager/releases/download/v$version/OuterWildsModManager-Portable.zip"
    }
}
